lambdata_marilynle/__init__.py
lambdata_marilynle/df_confidence_interval.py
lambdata_marilynle/df_utils.py
lambdata_marilynle-0.1.1.dist-info/LICENSE
lambdata_marilynle-0.1.1.dist-info/METADATA
lambdata_marilynle-0.1.1.dist-info/WHEEL
lambdata_marilynle-0.1.1.dist-info/top_level.txt
lambdata_marilynle-0.1.1.dist-info/RECORD
